cloudacious/Dynamo.py
cloudacious-0.0.3.dist-info/METADATA
cloudacious-0.0.3.dist-info/WHEEL
cloudacious-0.0.3.dist-info/RECORD
