Metadata-Version: 2.1
Name: cloudacious
Version: 0.0.3
Summary: 
Home-page: https://cloudacious.io
Author: SurfingDoggo
Author-email: git@surfingdoggo.com
Requires-Python: >=3.12,<4.0
Classifier: Programming Language :: Python :: 3
Classifier: Programming Language :: Python :: 3.12
Project-URL: Repository, https://gitlab.com/money-marathon/cloudacious/cloudacious
